LICENSE
MANIFEST.in
README.md
abstraction.py
abstraction_interface.py
naive_Bayes_classifier
setup.py
abstraction.egg-info/PKG-INFO
abstraction.egg-info/SOURCES.txt
abstraction.egg-info/dependency_links.txt
abstraction.egg-info/entry_points.txt
abstraction.egg-info/requires.txt
abstraction.egg-info/top_level.txt