Metadata-Version: 1.0
Name: abstraction
Version: 2016.6.17.1558
Summary: machine learning framework
Home-page: https://github.com/wdbm/abstraction
Author: Will Breaden Madden
Author-email: w.bm@cern.ch
License: GPLv3
Platform: UNKNOWN
